LICENSE
MANIFEST.in
README.md
setup.py
abjad_ext_nauert.egg-info/PKG-INFO
abjad_ext_nauert.egg-info/SOURCES.txt
abjad_ext_nauert.egg-info/dependency_links.txt
abjad_ext_nauert.egg-info/requires.txt
abjad_ext_nauert.egg-info/top_level.txt
abjadext/__init__.py
abjadext/py.typed
abjadext/nauert/__init__.py
abjadext/nauert/_version.py
abjadext/nauert/attackpointoptimizers.py
abjadext/nauert/gracehandlers.py
abjadext/nauert/heuristics.py
abjadext/nauert/jobhandlers.py
abjadext/nauert/qeventproxy.py
abjadext/nauert/qevents.py
abjadext/nauert/qeventsequence.py
abjadext/nauert/qgrid.py
abjadext/nauert/qschemaitems.py
abjadext/nauert/qschemas.py
abjadext/nauert/qtargetitems.py
abjadext/nauert/qtargets.py
abjadext/nauert/quantizationjob.py
abjadext/nauert/quantizer.py
abjadext/nauert/searchtrees.py
tests/test_BeatwiseQSchemaItem___new__.py
tests/test_BeatwiseQSchema___call__.py
tests/test_BeatwiseQSchema___getitem__.py
tests/test_BeatwiseQSchema___init__.py
tests/test_CollapsingGraceHandler___call__.py
tests/test_ConcatenatingGraceHandler___call__.py
tests/test_ConcatenatingGraceHandler___init__.py
tests/test_DiscardingGraceHandler___call__.py
tests/test_DistanceHeuristic___call__.py
tests/test_MeasurewiseAttackPointOptimizer___call__.py
tests/test_MeasurewiseQSchemaItem___new__.py
tests/test_MeasurewiseQSchema___call__.py
tests/test_MeasurewiseQSchema___getitem__.py
tests/test_MeasurewiseQSchema___init__.py
tests/test_ParallelJobHandler___call__.py
tests/test_QEvent.py
tests/test_QEventProxy___init__.py
tests/test_QEventSequence_from_millisecond_durations.py
tests/test_QEventSequence_from_millisecond_pitch_attachment_tuples.py
tests/test_QEventSequence_from_millisecond_pitch_pairs.py
tests/test_QEventSequence_from_tempo_scaled_durations.py
tests/test_QEventSequence_from_tempo_scaled_leaves.py
tests/test_QGridContainer___copy__.py
tests/test_QGridContainer___eq__.py
tests/test_QGridLeaf___copy__.py
tests/test_QGridLeaf___eq__.py
tests/test_QGrid___call__.py
tests/test_QGrid___copy__.py
tests/test_QGrid___eq__.py
tests/test_QGrid_distance.py
tests/test_QGrid_fit_q_events.py
tests/test_QGrid_pickle.py
tests/test_QGrid_subdivide_leaf.py
tests/test_QGrid_subdivide_leaves.py
