Metadata-Version: 2.2
Name: abjad-ext-nauert
Version: 3.21
Summary: Nauert extends Abjad with tools for rhythmic quantization.
Home-page: http://abjad.github.io
Author: Joséphine Wolf Oberholtzer, Tsz Kiu Pang
Author-email: josephine.wolf.oberholtzer@gmail.com, osamupang@gmail.com
License: MIT
Keywords: lilypond,music composition,music notation
Platform: Any
Classifier: Development Status :: 3 - Alpha
Classifier: License :: OSI Approved :: GNU General Public License (GPL)
Classifier: Programming Language :: Python :: 3.12
Classifier: Programming Language :: Python :: 3.13
Classifier: Topic :: Artistic Software
Requires-Python: >=3.12
License-File: LICENSE
Requires-Dist: abjad>=3.21
Dynamic: author
Dynamic: author-email
Dynamic: classifier
Dynamic: description
Dynamic: home-page
Dynamic: keywords
Dynamic: license
Dynamic: platform
Dynamic: requires-dist
Dynamic: requires-python
Dynamic: summary
